google_re2-1.1.20250722.dist-info/licenses/LICENSE
google_re2.libs/msvcp140-a4c2229bdc2a2a630acdc095b4d86008.dll
re2/__init__.py
re2/_re2.cp312-win_amd64.pyd
google_re2-1.1.20250722.dist-info/DELVEWHEEL
google_re2-1.1.20250722.dist-info/METADATA
google_re2-1.1.20250722.dist-info/WHEEL
google_re2-1.1.20250722.dist-info/top_level.txt
google_re2-1.1.20250722.dist-info/RECORD
