Metadata-Version: 2.4
Name: google-re2
Version: 1.1.20250722
Summary: RE2 Python bindings
Home-page: https://github.com/google/re2
Author: The RE2 Authors
Author-email: re2-dev@googlegroups.com
Classifier: Development Status :: 5 - Production/Stable
Classifier: Intended Audience :: Developers
Classifier: License :: OSI Approved :: BSD License
Classifier: Programming Language :: C++
Classifier: Programming Language :: Python :: 3.8
Requires-Python: ~=3.8
License-File: LICENSE
Dynamic: author
Dynamic: author-email
Dynamic: classifier
Dynamic: description
Dynamic: description-content-type
Dynamic: home-page
Dynamic: license-file
Dynamic: requires-python
Dynamic: summary
